{
    "image_name": "2.flv/2744.jpg",
    "body_info": [
        {
            "box": [
                635,
                42,
                1866,
                1079,
                29
            ],
            "action_cls": "walk",
            "img_action_cls": [
                "wave",
                "smoke"
            ],
            "keypoints": [],
            "adjacent_keypoints": []
        },
        {
            "box": [
                420,
                171,
                1193,
                1074,
                30
            ],
            "img_action_cls": [
                "wave",
                "smoke"
            ],
            "keypoints": [],
            "adjacent_keypoints": []
        },
        {
            "box": [
                0,
                50,
                700,
                1044,
                31
            ],
            "action_cls": "walk",
            "img_action_cls": [
                "walk",
                "other"
            ],
            "keypoints": [],
            "adjacent_keypoints": []
        }
    ],
    "face_info": [
        {
            "key_points": [
                [
                    664,
                    278
                ],
                [
                    659,
                    327
                ],
                [
                    657,
                    377
                ],
                [
                    657,
                    426
                ],
                [
                    666,
                    469
                ],
                [
                    683,
                    505
                ],
                [
                    708,
                    530
                ],
                [
                    733,
                    553
                ],
                [
                    766,
                    570
                ],
                [
                    802,
                    574
                ],
                [
                    835,
                    567
                ],
                [
                    869,
                    554
                ],
                [
                    895,
                    530
                ],
                [
                    913,
                    494
                ],
                [
                    928,
                    456
                ],
                [
                    942,
                    414
                ],
                [
                    952,
                    367
                ],
                [
                    708,
                    207
                ],
                [
                    735,
                    191
                ],
                [
                    762,
                    192
                ],
                [
                    789,
                    201
                ],
                [
                    814,
                    217
                ],
                [
                    857,
                    229
                ],
                [
                    885,
                    230
                ],
                [
                    913,
                    236
                ],
                [
                    936,
                    253
                ],
                [
                    949,
                    281
                ],
                [
                    829,
                    255
                ],
                [
                    824,
                    281
                ],
                [
                    819,
                    305
                ],
                [
                    814,
                    332
                ],
                [
                    780,
                    368
                ],
                [
                    793,
                    373
                ],
                [
                    806,
                    381
                ],
                [
                    820,
                    383
                ],
                [
                    835,
                    384
                ],
                [
                    731,
                    248
                ],
                [
                    747,
                    237
                ],
                [
                    764,
                    239
                ],
                [
                    778,
                    257
                ],
                [
                    760,
                    255
                ],
                [
                    744,
                    253
                ],
                [
                    865,
                    278
                ],
                [
                    884,
                    269
                ],
                [
                    902,
                    279
                ],
                [
                    915,
                    300
                ],
                [
                    897,
                    296
                ],
                [
                    879,
                    287
                ],
                [
                    736,
                    449
                ],
                [
                    758,
                    434
                ],
                [
                    782,
                    427
                ],
                [
                    794,
                    436
                ],
                [
                    806,
                    435
                ],
                [
                    823,
                    453
                ],
                [
                    835,
                    482
                ],
                [
                    816,
                    488
                ],
                [
                    797,
                    489
                ],
                [
                    784,
                    487
                ],
                [
                    770,
                    481
                ],
                [
                    750,
                    470
                ],
                [
                    744,
                    449
                ],
                [
                    779,
                    444
                ],
                [
                    792,
                    449
                ],
                [
                    804,
                    452
                ],
                [
                    826,
                    477
                ],
                [
                    801,
                    462
                ],
                [
                    789,
                    459
                ],
                [
                    776,
                    455
                ]
            ],
            "face_coordinate": [
                682,
                164,
                976,
                561
            ],
            "expression": "amazing",
            "attention_score": 0.7250000000000001
        },
        {
            "key_points": [
                [
                    1096,
                    160
                ],
                [
                    1089,
                    221
                ],
                [
                    1087,
                    283
                ],
                [
                    1082,
                    340
                ],
                [
                    1092,
                    393
                ],
                [
                    1115,
                    435
                ],
                [
                    1147,
                    469
                ],
                [
                    1180,
                    495
                ],
                [
                    1212,
                    513
                ],
                [
                    1246,
                    515
                ],
                [
                    1277,
                    493
                ],
                [
                    1301,
                    467
                ],
                [
                    1321,
                    436
                ],
                [
                    1337,
                    399
                ],
                [
                    1349,
                    364
                ],
                [
                    1361,
                    325
                ],
                [
                    1369,
                    285
                ],
                [
                    1172,
                    147
                ],
                [
                    1205,
                    141
                ],
                [
                    1239,
                    152
                ],
                [
                    1266,
                    172
                ],
                [
                    1288,
                    200
                ],
                [
                    1327,
                    229
                ],
                [
                    1345,
                    226
                ],
                [
                    1362,
                    226
                ],
                [
                    1376,
                    234
                ],
                [
                    1384,
                    250
                ],
                [
                    1298,
                    241
                ],
                [
                    1299,
                    278
                ],
                [
                    1299,
                    316
                ],
                [
                    1300,
                    354
                ],
                [
                    1250,
                    350
                ],
                [
                    1265,
                    364
                ],
                [
                    1280,
                    379
                ],
                [
                    1296,
                    376
                ],
                [
                    1310,
                    368
                ],
                [
                    1200,
                    184
                ],
                [
                    1219,
                    183
                ],
                [
                    1237,
                    194
                ],
                [
                    1248,
                    217
                ],
                [
                    1229,
                    211
                ],
                [
                    1213,
                    201
                ],
                [
                    1314,
                    254
                ],
                [
                    1329,
                    249
                ],
                [
                    1345,
                    256
                ],
                [
                    1353,
                    269
                ],
                [
                    1340,
                    272
                ],
                [
                    1326,
                    265
                ],
                [
                    1185,
                    380
                ],
                [
                    1226,
                    394
                ],
                [
                    1257,
                    404
                ],
                [
                    1271,
                    415
                ],
                [
                    1283,
                    415
                ],
                [
                    1293,
                    423
                ],
                [
                    1293,
                    430
                ],
                [
                    1279,
                    435
                ],
                [
                    1263,
                    439
                ],
                [
                    1250,
                    435
                ],
                [
                    1236,
                    425
                ],
                [
                    1212,
                    407
                ],
                [
                    1196,
                    388
                ],
                [
                    1250,
                    413
                ],
                [
                    1265,
                    423
                ],
                [
                    1276,
                    428
                ],
                [
                    1288,
                    428
                ],
                [
                    1271,
                    416
                ],
                [
                    1260,
                    413
                ],
                [
                    1246,
                    404
                ]
            ],
            "face_coordinate": [
                1118,
                93,
                1439,
                512
            ],
            "expression": "nature",
            "attention_score": 0.22727272727272727
        }
    ]
}