{
    "image_name": "2.flv/2798.jpg",
    "body_info": [
        {
            "box": [
                834,
                62,
                1900,
                1079,
                29
            ],
            "action_cls": "walk",
            "img_action_cls": [
                "wave",
                "smoke"
            ],
            "keypoints": [],
            "adjacent_keypoints": []
        },
        {
            "box": [
                384,
                182,
                1184,
                1077,
                30
            ],
            "img_action_cls": [
                "wave",
                "smoke"
            ],
            "keypoints": [],
            "adjacent_keypoints": []
        },
        {
            "box": [
                0,
                59,
                675,
                1035,
                31
            ],
            "action_cls": "walk",
            "img_action_cls": [
                "walk",
                "other"
            ],
            "keypoints": [],
            "adjacent_keypoints": []
        }
    ],
    "face_info": [
        {
            "key_points": [
                [
                    1068,
                    261
                ],
                [
                    1067,
                    312
                ],
                [
                    1069,
                    361
                ],
                [
                    1076,
                    410
                ],
                [
                    1093,
                    455
                ],
                [
                    1119,
                    492
                ],
                [
                    1160,
                    516
                ],
                [
                    1199,
                    532
                ],
                [
                    1238,
                    535
                ],
                [
                    1271,
                    527
                ],
                [
                    1297,
                    507
                ],
                [
                    1321,
                    475
                ],
                [
                    1336,
                    440
                ],
                [
                    1349,
                    403
                ],
                [
                    1358,
                    364
                ],
                [
                    1362,
                    322
                ],
                [
                    1361,
                    283
                ],
                [
                    1139,
                    196
                ],
                [
                    1165,
                    177
                ],
                [
                    1194,
                    170
                ],
                [
                    1223,
                    174
                ],
                [
                    1250,
                    189
                ],
                [
                    1284,
                    202
                ],
                [
                    1308,
                    197
                ],
                [
                    1332,
                    195
                ],
                [
                    1353,
                    207
                ],
                [
                    1363,
                    230
                ],
                [
                    1263,
                    238
                ],
                [
                    1266,
                    266
                ],
                [
                    1269,
                    295
                ],
                [
                    1272,
                    326
                ],
                [
                    1228,
                    352
                ],
                [
                    1244,
                    357
                ],
                [
                    1262,
                    365
                ],
                [
                    1278,
                    361
                ],
                [
                    1291,
                    354
                ],
                [
                    1161,
                    228
                ],
                [
                    1178,
                    217
                ],
                [
                    1197,
                    219
                ],
                [
                    1213,
                    237
                ],
                [
                    1194,
                    238
                ],
                [
                    1175,
                    238
                ],
                [
                    1291,
                    249
                ],
                [
                    1308,
                    237
                ],
                [
                    1327,
                    239
                ],
                [
                    1340,
                    254
                ],
                [
                    1327,
                    258
                ],
                [
                    1307,
                    256
                ],
                [
                    1184,
                    413
                ],
                [
                    1215,
                    406
                ],
                [
                    1242,
                    402
                ],
                [
                    1258,
                    406
                ],
                [
                    1269,
                    402
                ],
                [
                    1281,
                    409
                ],
                [
                    1294,
                    418
                ],
                [
                    1278,
                    421
                ],
                [
                    1265,
                    426
                ],
                [
                    1252,
                    428
                ],
                [
                    1236,
                    429
                ],
                [
                    1211,
                    423
                ],
                [
                    1192,
                    413
                ],
                [
                    1240,
                    419
                ],
                [
                    1257,
                    420
                ],
                [
                    1267,
                    419
                ],
                [
                    1286,
                    417
                ],
                [
                    1266,
                    404
                ],
                [
                    1255,
                    407
                ],
                [
                    1239,
                    406
                ]
            ],
            "face_coordinate": [
                1104,
                121,
                1418,
                504
            ],
            "expression": "nature",
            "attention_score": 0.9672727272727273
        },
        {
            "key_points": [
                [
                    680,
                    303
                ],
                [
                    677,
                    354
                ],
                [
                    678,
                    403
                ],
                [
                    684,
                    450
                ],
                [
                    698,
                    492
                ],
                [
                    717,
                    527
                ],
                [
                    744,
                    552
                ],
                [
                    770,
                    572
                ],
                [
                    803,
                    583
                ],
                [
                    838,
                    588
                ],
                [
                    871,
                    579
                ],
                [
                    901,
                    561
                ],
                [
                    924,
                    534
                ],
                [
                    941,
                    500
                ],
                [
                    954,
                    462
                ],
                [
                    968,
                    420
                ],
                [
                    977,
                    372
                ],
                [
                    722,
                    242
                ],
                [
                    747,
                    220
                ],
                [
                    776,
                    218
                ],
                [
                    804,
                    227
                ],
                [
                    831,
                    244
                ],
                [
                    876,
                    255
                ],
                [
                    901,
                    251
                ],
                [
                    928,
                    256
                ],
                [
                    951,
                    270
                ],
                [
                    964,
                    296
                ],
                [
                    849,
                    275
                ],
                [
                    847,
                    300
                ],
                [
                    844,
                    324
                ],
                [
                    841,
                    351
                ],
                [
                    807,
                    391
                ],
                [
                    820,
                    395
                ],
                [
                    833,
                    400
                ],
                [
                    847,
                    402
                ],
                [
                    862,
                    402
                ],
                [
                    746,
                    269
                ],
                [
                    763,
                    256
                ],
                [
                    783,
                    258
                ],
                [
                    799,
                    280
                ],
                [
                    780,
                    280
                ],
                [
                    760,
                    277
                ],
                [
                    887,
                    297
                ],
                [
                    905,
                    284
                ],
                [
                    925,
                    291
                ],
                [
                    937,
                    313
                ],
                [
                    921,
                    313
                ],
                [
                    902,
                    306
                ],
                [
                    765,
                    477
                ],
                [
                    787,
                    454
                ],
                [
                    812,
                    445
                ],
                [
                    823,
                    452
                ],
                [
                    835,
                    449
                ],
                [
                    852,
                    467
                ],
                [
                    866,
                    501
                ],
                [
                    846,
                    507
                ],
                [
                    828,
                    510
                ],
                [
                    815,
                    509
                ],
                [
                    802,
                    506
                ],
                [
                    781,
                    496
                ],
                [
                    773,
                    476
                ],
                [
                    809,
                    461
                ],
                [
                    821,
                    465
                ],
                [
                    833,
                    467
                ],
                [
                    857,
                    495
                ],
                [
                    831,
                    485
                ],
                [
                    820,
                    485
                ],
                [
                    807,
                    481
                ]
            ],
            "face_coordinate": [
                713,
                200,
                991,
                567
            ],
            "expression": "amazing",
            "attention_score": 0.7625
        }
    ]
}