{
    "image_name": "2.flv/396.jpg",
    "body_info": [
        {
            "box": [
                1254,
                212,
                1885,
                1070,
                1
            ],
            "action_cls": "walk",
            "img_action_cls": [
                "wave",
                "other"
            ],
            "keypoints": [],
            "adjacent_keypoints": []
        },
        {
            "box": [
                153,
                207,
                797,
                1078,
                2
            ],
            "img_action_cls": [
                "wave",
                "smoke"
            ],
            "keypoints": [],
            "adjacent_keypoints": []
        },
        {
            "box": [
                440,
                177,
                1181,
                1078,
                3
            ],
            "img_action_cls": [
                "stand",
                "smoke"
            ],
            "keypoints": [],
            "adjacent_keypoints": []
        }
    ],
    "face_info": [
        {
            "key_points": [
                [
                    332,
                    341
                ],
                [
                    329,
                    370
                ],
                [
                    330,
                    401
                ],
                [
                    332,
                    433
                ],
                [
                    337,
                    465
                ],
                [
                    349,
                    491
                ],
                [
                    368,
                    509
                ],
                [
                    387,
                    524
                ],
                [
                    410,
                    531
                ],
                [
                    434,
                    530
                ],
                [
                    458,
                    522
                ],
                [
                    480,
                    510
                ],
                [
                    498,
                    490
                ],
                [
                    514,
                    462
                ],
                [
                    524,
                    436
                ],
                [
                    533,
                    405
                ],
                [
                    537,
                    376
                ],
                [
                    350,
                    310
                ],
                [
                    366,
                    298
                ],
                [
                    385,
                    294
                ],
                [
                    406,
                    295
                ],
                [
                    424,
                    304
                ],
                [
                    455,
                    310
                ],
                [
                    474,
                    306
                ],
                [
                    495,
                    309
                ],
                [
                    513,
                    317
                ],
                [
                    525,
                    333
                ],
                [
                    434,
                    322
                ],
                [
                    432,
                    337
                ],
                [
                    429,
                    350
                ],
                [
                    426,
                    365
                ],
                [
                    405,
                    397
                ],
                [
                    414,
                    400
                ],
                [
                    423,
                    401
                ],
                [
                    433,
                    402
                ],
                [
                    444,
                    402
                ],
                [
                    365,
                    332
                ],
                [
                    378,
                    322
                ],
                [
                    393,
                    322
                ],
                [
                    405,
                    333
                ],
                [
                    391,
                    336
                ],
                [
                    377,
                    337
                ],
                [
                    465,
                    339
                ],
                [
                    479,
                    330
                ],
                [
                    493,
                    333
                ],
                [
                    504,
                    345
                ],
                [
                    492,
                    347
                ],
                [
                    477,
                    345
                ],
                [
                    382,
                    454
                ],
                [
                    395,
                    439
                ],
                [
                    410,
                    429
                ],
                [
                    419,
                    435
                ],
                [
                    429,
                    431
                ],
                [
                    444,
                    444
                ],
                [
                    456,
                    467
                ],
                [
                    442,
                    480
                ],
                [
                    426,
                    484
                ],
                [
                    415,
                    482
                ],
                [
                    405,
                    480
                ],
                [
                    392,
                    471
                ],
                [
                    388,
                    453
                ],
                [
                    408,
                    446
                ],
                [
                    418,
                    448
                ],
                [
                    428,
                    448
                ],
                [
                    449,
                    464
                ],
                [
                    428,
                    461
                ],
                [
                    418,
                    461
                ],
                [
                    408,
                    458
                ]
            ],
            "face_coordinate": [
                332,
                266,
                532,
                502
            ],
            "expression": "amazing",
            "attention_score": 0.835
        },
        {
            "key_points": [
                [
                    795,
                    300
                ],
                [
                    790,
                    333
                ],
                [
                    789,
                    369
                ],
                [
                    791,
                    403
                ],
                [
                    799,
                    434
                ],
                [
                    811,
                    462
                ],
                [
                    827,
                    485
                ],
                [
                    843,
                    506
                ],
                [
                    865,
                    518
                ],
                [
                    892,
                    517
                ],
                [
                    923,
                    506
                ],
                [
                    952,
                    491
                ],
                [
                    976,
                    467
                ],
                [
                    991,
                    433
                ],
                [
                    998,
                    393
                ],
                [
                    1004,
                    351
                ],
                [
                    1006,
                    312
                ],
                [
                    795,
                    269
                ],
                [
                    806,
                    256
                ],
                [
                    822,
                    253
                ],
                [
                    840,
                    257
                ],
                [
                    857,
                    267
                ],
                [
                    885,
                    272
                ],
                [
                    907,
                    263
                ],
                [
                    931,
                    261
                ],
                [
                    954,
                    269
                ],
                [
                    971,
                    285
                ],
                [
                    869,
                    293
                ],
                [
                    865,
                    308
                ],
                [
                    861,
                    323
                ],
                [
                    856,
                    340
                ],
                [
                    842,
                    374
                ],
                [
                    851,
                    376
                ],
                [
                    862,
                    377
                ],
                [
                    874,
                    377
                ],
                [
                    886,
                    376
                ],
                [
                    813,
                    290
                ],
                [
                    824,
                    281
                ],
                [
                    837,
                    282
                ],
                [
                    850,
                    294
                ],
                [
                    836,
                    296
                ],
                [
                    823,
                    295
                ],
                [
                    906,
                    298
                ],
                [
                    919,
                    288
                ],
                [
                    934,
                    289
                ],
                [
                    948,
                    298
                ],
                [
                    933,
                    304
                ],
                [
                    918,
                    302
                ],
                [
                    830,
                    428
                ],
                [
                    839,
                    411
                ],
                [
                    852,
                    404
                ],
                [
                    862,
                    407
                ],
                [
                    872,
                    404
                ],
                [
                    892,
                    413
                ],
                [
                    915,
                    433
                ],
                [
                    895,
                    454
                ],
                [
                    875,
                    461
                ],
                [
                    864,
                    461
                ],
                [
                    853,
                    459
                ],
                [
                    839,
                    451
                ],
                [
                    835,
                    427
                ],
                [
                    853,
                    417
                ],
                [
                    862,
                    418
                ],
                [
                    873,
                    418
                ],
                [
                    908,
                    432
                ],
                [
                    874,
                    441
                ],
                [
                    863,
                    440
                ],
                [
                    853,
                    439
                ]
            ],
            "face_coordinate": [
                785,
                219,
                996,
                502
            ],
            "expression": "amazing",
            "attention_score": 0.825
        },
        {
            "key_points": [
                [
                    1448,
                    281
                ],
                [
                    1442,
                    316
                ],
                [
                    1442,
                    351
                ],
                [
                    1443,
                    387
                ],
                [
                    1451,
                    423
                ],
                [
                    1465,
                    460
                ],
                [
                    1480,
                    494
                ],
                [
                    1498,
                    525
                ],
                [
                    1525,
                    544
                ],
                [
                    1555,
                    548
                ],
                [
                    1585,
                    533
                ],
                [
                    1611,
                    511
                ],
                [
                    1636,
                    485
                ],
                [
                    1656,
                    455
                ],
                [
                    1670,
                    423
                ],
                [
                    1682,
                    387
                ],
                [
                    1688,
                    349
                ],
                [
                    1472,
                    251
                ],
                [
                    1495,
                    245
                ],
                [
                    1518,
                    250
                ],
                [
                    1540,
                    261
                ],
                [
                    1561,
                    279
                ],
                [
                    1597,
                    298
                ],
                [
                    1620,
                    292
                ],
                [
                    1643,
                    295
                ],
                [
                    1663,
                    304
                ],
                [
                    1678,
                    319
                ],
                [
                    1573,
                    314
                ],
                [
                    1570,
                    346
                ],
                [
                    1567,
                    378
                ],
                [
                    1563,
                    410
                ],
                [
                    1529,
                    409
                ],
                [
                    1542,
                    422
                ],
                [
                    1557,
                    433
                ],
                [
                    1573,
                    431
                ],
                [
                    1587,
                    426
                ],
                [
                    1488,
                    284
                ],
                [
                    1503,
                    281
                ],
                [
                    1519,
                    287
                ],
                [
                    1533,
                    302
                ],
                [
                    1514,
                    302
                ],
                [
                    1498,
                    297
                ],
                [
                    1606,
                    327
                ],
                [
                    1624,
                    321
                ],
                [
                    1641,
                    327
                ],
                [
                    1655,
                    339
                ],
                [
                    1638,
                    343
                ],
                [
                    1621,
                    337
                ],
                [
                    1489,
                    437
                ],
                [
                    1514,
                    445
                ],
                [
                    1534,
                    454
                ],
                [
                    1548,
                    462
                ],
                [
                    1562,
                    462
                ],
                [
                    1582,
                    466
                ],
                [
                    1601,
                    471
                ],
                [
                    1575,
                    491
                ],
                [
                    1551,
                    496
                ],
                [
                    1536,
                    493
                ],
                [
                    1521,
                    485
                ],
                [
                    1504,
                    466
                ],
                [
                    1496,
                    443
                ],
                [
                    1530,
                    461
                ],
                [
                    1545,
                    469
                ],
                [
                    1560,
                    471
                ],
                [
                    1594,
                    470
                ],
                [
                    1556,
                    476
                ],
                [
                    1542,
                    473
                ],
                [
                    1527,
                    465
                ]
            ],
            "face_coordinate": [
                1450,
                238,
                1707,
                526
            ],
            "expression": "nature",
            "attention_score": 0.8647727272727272
        }
    ]
}