{
    "image_name": "3.mp4/16.jpg",
    "body_info": [
        {
            "box": [
                205,
                48,
                312,
                327,
                1
            ],
            "img_action_cls": [
                "walk",
                "other"
            ],
            "keypoints": [
                [
                    48.72972487174359,
                    13.758275419801144,
                    9.93889331817627
                ],
                [
                    56.000675528319846,
                    7.354845937791761,
                    9.856014847755432
                ],
                [
                    43.17086394791751,
                    7.738876175094436,
                    9.575397968292236
                ],
                [
                    67.77303391387782,
                    12.991663007945803,
                    8.967639803886414
                ],
                [
                    82.97001176027908,
                    48.46165111038711,
                    9.105044603347778
                ],
                [
                    35.41696910683027,
                    49.71519381004375,
                    9.961854815483093
                ],
                [
                    89.87336340270092,
                    90.24850485351058,
                    9.843436479568481
                ],
                [
                    21.880001097610318,
                    94.86363994682227,
                    9.705923199653625
                ],
                [
                    86.72747836162135,
                    132.50107000162313,
                    3.7635692954063416
                ],
                [
                    9.180346346393074,
                    131.91090378001496,
                    9.581355452537537
                ],
                [
                    76.03971217833843,
                    138.13203171321322,
                    9.810588955879211
                ],
                [
                    41.54023542109224,
                    138.49776465552193,
                    9.614732265472412
                ],
                [
                    81.33759432232257,
                    208.16186575837187,
                    9.416566491127014
                ],
                [
                    37.85132182996298,
                    207.93709708308123,
                    9.812015295028687
                ],
                [
                    84.08511407596549,
                    261.1318819437708,
                    8.337381482124329
                ],
                [
                    30.928838543056216,
                    263.7039097167633,
                    8.697683811187744
                ]
            ],
            "adjacent_keypoints": [
                [
                    [
                        76,
                        138
                    ],
                    [
                        82,
                        48
                    ]
                ],
                [
                    [
                        89,
                        90
                    ],
                    [
                        82,
                        48
                    ]
                ],
                [
                    [
                        89,
                        90
                    ],
                    [
                        86,
                        132
                    ]
                ],
                [
                    [
                        76,
                        138
                    ],
                    [
                        81,
                        208
                    ]
                ],
                [
                    [
                        81,
                        208
                    ],
                    [
                        84,
                        261
                    ]
                ],
                [
                    [
                        41,
                        138
                    ],
                    [
                        35,
                        49
                    ]
                ],
                [
                    [
                        21,
                        94
                    ],
                    [
                        35,
                        49
                    ]
                ],
                [
                    [
                        21,
                        94
                    ],
                    [
                        9,
                        131
                    ]
                ],
                [
                    [
                        41,
                        138
                    ],
                    [
                        37,
                        207
                    ]
                ],
                [
                    [
                        37,
                        207
                    ],
                    [
                        30,
                        263
                    ]
                ],
                [
                    [
                        82,
                        48
                    ],
                    [
                        35,
                        49
                    ]
                ],
                [
                    [
                        76,
                        138
                    ],
                    [
                        41,
                        138
                    ]
                ]
            ]
        }
    ],
    "face_info": [
        {
            "key_points": [
                [
                    248,
                    58
                ],
                [
                    248,
                    62
                ],
                [
                    249,
                    64
                ],
                [
                    250,
                    67
                ],
                [
                    251,
                    70
                ],
                [
                    252,
                    72
                ],
                [
                    254,
                    74
                ],
                [
                    256,
                    75
                ],
                [
                    258,
                    76
                ],
                [
                    261,
                    75
                ],
                [
                    265,
                    75
                ],
                [
                    268,
                    73
                ],
                [
                    270,
                    71
                ],
                [
                    272,
                    68
                ],
                [
                    273,
                    65
                ],
                [
                    273,
                    61
                ],
                [
                    273,
                    57
                ],
                [
                    249,
                    54
                ],
                [
                    249,
                    51
                ],
                [
                    251,
                    50
                ],
                [
                    253,
                    50
                ],
                [
                    255,
                    51
                ],
                [
                    258,
                    50
                ],
                [
                    261,
                    49
                ],
                [
                    264,
                    49
                ],
                [
                    266,
                    51
                ],
                [
                    268,
                    53
                ],
                [
                    257,
                    54
                ],
                [
                    257,
                    56
                ],
                [
                    256,
                    58
                ],
                [
                    256,
                    60
                ],
                [
                    255,
                    63
                ],
                [
                    256,
                    63
                ],
                [
                    257,
                    63
                ],
                [
                    258,
                    63
                ],
                [
                    259,
                    63
                ],
                [
                    251,
                    56
                ],
                [
                    252,
                    55
                ],
                [
                    253,
                    55
                ],
                [
                    255,
                    56
                ],
                [
                    253,
                    56
                ],
                [
                    252,
                    57
                ],
                [
                    261,
                    56
                ],
                [
                    262,
                    54
                ],
                [
                    264,
                    54
                ],
                [
                    266,
                    55
                ],
                [
                    264,
                    56
                ],
                [
                    262,
                    56
                ],
                [
                    254,
                    68
                ],
                [
                    255,
                    66
                ],
                [
                    256,
                    65
                ],
                [
                    257,
                    65
                ],
                [
                    258,
                    64
                ],
                [
                    260,
                    65
                ],
                [
                    262,
                    68
                ],
                [
                    260,
                    68
                ],
                [
                    258,
                    69
                ],
                [
                    257,
                    69
                ],
                [
                    256,
                    69
                ],
                [
                    255,
                    68
                ],
                [
                    255,
                    67
                ],
                [
                    256,
                    66
                ],
                [
                    257,
                    66
                ],
                [
                    258,
                    66
                ],
                [
                    261,
                    67
                ],
                [
                    258,
                    67
                ],
                [
                    257,
                    67
                ],
                [
                    256,
                    67
                ]
            ],
            "face_coordinate": [
                244,
                39,
                277,
                78
            ],
            "expression": "happy",
            "attention_score": 0.845
        }
    ]
}