{
    "image_name": "3.mp4/255.jpg",
    "body_info": [
        {
            "box": [
                98,
                105,
                366,
                335,
                1
            ],
            "action_cls": "clap",
            "img_action_cls": [
                "walk",
                "phone"
            ],
            "keypoints": [
                [
                    115.53107828852733,
                    35.4913369708591,
                    9.971463084220886
                ],
                [
                    121.62286753969899,
                    30.370615863800047,
                    9.943801760673523
                ],
                [
                    110.04961067229394,
                    30.057006486256913,
                    9.896010756492615
                ],
                [
                    127.90907309862428,
                    33.41527874469757,
                    7.05535352230072
                ],
                [
                    103.72967936742167,
                    34.25652207268609,
                    5.4441529512405396
                ],
                [
                    143.62141804379712,
                    68.09955329895018,
                    9.889867305755615
                ],
                [
                    98.26959558961921,
                    69.08617361916436,
                    9.960066676139832
                ],
                [
                    165.18256464264275,
                    112.97122264438204,
                    8.493539094924927
                ],
                [
                    72.39376638093347,
                    97.9917377895779,
                    7.650321125984192
                ],
                [
                    167.8865372633656,
                    159.59291975233288,
                    8.43226671218872
                ],
                [
                    46.070625008312184,
                    125.98586485120984,
                    3.5881271958351135
                ],
                [
                    144.45865987339837,
                    146.05516521135965,
                    9.084492921829224
                ],
                [
                    106.93323837458392,
                    141.51648008558485,
                    8.943146467208862
                ],
                [
                    61.2929683047046,
                    141.83142064412434,
                    4.906183481216431
                ],
                [
                    76.21375843151999,
                    212.79655380249022,
                    8.27907145023346
                ]
            ],
            "adjacent_keypoints": [
                [
                    [
                        144,
                        146
                    ],
                    [
                        143,
                        68
                    ]
                ],
                [
                    [
                        165,
                        112
                    ],
                    [
                        143,
                        68
                    ]
                ],
                [
                    [
                        165,
                        112
                    ],
                    [
                        167,
                        159
                    ]
                ],
                [
                    [
                        106,
                        141
                    ],
                    [
                        98,
                        69
                    ]
                ],
                [
                    [
                        72,
                        97
                    ],
                    [
                        98,
                        69
                    ]
                ],
                [
                    [
                        72,
                        97
                    ],
                    [
                        46,
                        125
                    ]
                ],
                [
                    [
                        106,
                        141
                    ],
                    [
                        61,
                        141
                    ]
                ],
                [
                    [
                        61,
                        141
                    ],
                    [
                        76,
                        212
                    ]
                ],
                [
                    [
                        143,
                        68
                    ],
                    [
                        98,
                        69
                    ]
                ],
                [
                    [
                        144,
                        146
                    ],
                    [
                        106,
                        141
                    ]
                ]
            ]
        }
    ],
    "face_info": [
        {
            "key_points": [
                [
                    200,
                    132
                ],
                [
                    200,
                    136
                ],
                [
                    201,
                    140
                ],
                [
                    201,
                    144
                ],
                [
                    202,
                    147
                ],
                [
                    204,
                    151
                ],
                [
                    206,
                    153
                ],
                [
                    209,
                    155
                ],
                [
                    212,
                    156
                ],
                [
                    215,
                    156
                ],
                [
                    219,
                    155
                ],
                [
                    222,
                    153
                ],
                [
                    224,
                    150
                ],
                [
                    226,
                    147
                ],
                [
                    228,
                    143
                ],
                [
                    229,
                    138
                ],
                [
                    229,
                    134
                ],
                [
                    203,
                    125
                ],
                [
                    205,
                    123
                ],
                [
                    207,
                    122
                ],
                [
                    210,
                    122
                ],
                [
                    213,
                    123
                ],
                [
                    217,
                    124
                ],
                [
                    219,
                    123
                ],
                [
                    223,
                    124
                ],
                [
                    225,
                    125
                ],
                [
                    227,
                    128
                ],
                [
                    214,
                    129
                ],
                [
                    214,
                    132
                ],
                [
                    214,
                    135
                ],
                [
                    214,
                    139
                ],
                [
                    211,
                    141
                ],
                [
                    212,
                    142
                ],
                [
                    214,
                    142
                ],
                [
                    215,
                    142
                ],
                [
                    216,
                    142
                ],
                [
                    205,
                    129
                ],
                [
                    207,
                    127
                ],
                [
                    209,
                    127
                ],
                [
                    210,
                    130
                ],
                [
                    209,
                    130
                ],
                [
                    206,
                    130
                ],
                [
                    219,
                    131
                ],
                [
                    220,
                    129
                ],
                [
                    222,
                    129
                ],
                [
                    224,
                    131
                ],
                [
                    222,
                    132
                ],
                [
                    220,
                    131
                ],
                [
                    209,
                    146
                ],
                [
                    211,
                    144
                ],
                [
                    212,
                    144
                ],
                [
                    214,
                    144
                ],
                [
                    215,
                    144
                ],
                [
                    217,
                    145
                ],
                [
                    218,
                    147
                ],
                [
                    216,
                    148
                ],
                [
                    215,
                    149
                ],
                [
                    213,
                    149
                ],
                [
                    212,
                    148
                ],
                [
                    210,
                    147
                ],
                [
                    210,
                    146
                ],
                [
                    212,
                    146
                ],
                [
                    213,
                    146
                ],
                [
                    215,
                    146
                ],
                [
                    217,
                    147
                ],
                [
                    215,
                    146
                ],
                [
                    213,
                    147
                ],
                [
                    212,
                    146
                ]
            ],
            "face_coordinate": [
                198,
                114,
                232,
                156
            ],
            "expression": "nature",
            "attention_score": 0.9472727272727273
        }
    ]
}